[{"title":"Title 0","description":"Description 0","link":"Link 0"},{"title":"Title 1","description":"Description 1","link":"Link 1"},{"title":"Title 2","description":"Description 2","link":"Link 2"},{"title":"Title 3","description":"Description 3"},{"title":"Title 4","description":"Description 4","link":"Link 4"},{"title":"Title 5","description":"Description 5"},{"title":"Title 6","description":"Description 6","link":"Link 6"},{"title":"Title 7","description":"Description 7"},{"title":"Title 8","description":"Description 8","link":"Link 8"},{"title":"Title 9","description":"Description 9","link":"Link 9"},{"title":"Title 10","description":"Description 10","link":"Link 10"},{"title":"Title 11","description":"Description 11"},{"title":"Title 12","description":"Description 12","link":"Link 12"},{"title":"Title 13","description":"Description 13","link":"Link 13"},{"title":"Title 14","description":"Description 14"},{"title":"Title 15","description":"Description 15"},{"title":"Title 16","description":"Description 16"},{"title":"Title 17","description":"Description 17"},{"title":"Title 18","description":"Description 18","link":"Link 18"},{"title":"Title 19","description":"Description 19","link":"Link 19"},{"title":"Title 20","description":"Description 20"},{"title":"Title 21","description":"Description 21","link":"Link 21"},{"title":"Title 22","description":"Description 22"},{"title":"Title 23","description":"Description 23"},{"title":"Title 24","description":"Description 24"},{"title":"Title 25","description":"Description 25"},{"title":"Title 26","description":"Description 26","link":"Link 26"},{"title":"Title 27","description":"Description 27","link":"Link 27"},{"title":"Title 28","description":"Description 28"},{"title":"Title 29","description":"Description 29","link":"Link 29"},{"title":"Title 30","description":"Description 30","link":"Link 30"},{"title":"Title 31","description":"Description 31"},{"title":"Title 32","description":"Description 32","link":"Link 32"},{"title":"Title 33","description":"Description 33","link":"Link 33"},{"title":"Title 34","description":"Description 34","link":"Link 34"},{"title":"Title 35","description":"Description 35","link":"Link 35"},{"title":"Title 36","description":"Description 36","link":"Link 36"},{"title":"Title 37","description":"Description 37","link":"Link 37"},{"title":"Title 38","description":"Description 38","link":"Link 38"},{"title":"Title 39","description":"Description 39"},{"title":"Title 40","description":"Description 40","link":"Link 40"},{"title":"Title 41","description":"Description 41"},{"title":"Title 42","description":"Description 42"},{"title":"Title 43","description":"Description 43","link":"Link 43"},{"title":"Title 44","description":"Description 44","link":"Link 44"},{"title":"Title 45","description":"Description 45"},{"title":"Title 46","description":"Description 46"},{"title":"Title 47","description":"Description 47"},{"title":"Title 48","description":"Description 48"},{"title":"Title 49","description":"Description 49"},{"title":"Title 50","description":"Description 50","link":"Link 50"},{"title":"Title 51","description":"Description 51","link":"Link 51"},{"title":"Title 52","description":"Description 52"},{"title":"Title 53","description":"Description 53","link":"Link 53"},{"title":"Title 54","description":"Description 54"},{"title":"Title 55","description":"Description 55"},{"title":"Title 56","description":"Description 56"},{"title":"Title 57","description":"Description 57"},{"title":"Title 58","description":"Description 58","link":"Link 58"},{"title":"Title 59","description":"Description 59","link":"Link 59"},{"title":"Title 60","description":"Description 60","link":"Link 60"},{"title":"Title 61","description":"Description 61"},{"title":"Title 62","description":"Description 62"},{"title":"Title 63","description":"Description 63"},{"title":"Title 64","description":"Description 64","link":"Link 64"},{"title":"Title 65","description":"Description 65"},{"title":"Title 66","description":"Description 66","link":"Link 66"},{"title":"Title 67","description":"Description 67"},{"title":"Title 68","description":"Description 68","link":"Link 68"},{"title":"Title 69","description":"Description 69","link":"Link 69"},{"title":"Title 70","description":"Description 70","link":"Link 70"},{"title":"Title 71","description":"Description 71"},{"title":"Title 72","description":"Description 72","link":"Link 72"},{"title":"Title 73","description":"Description 73","link":"Link 73"},{"title":"Title 74","description":"Description 74"},{"title":"Title 75","description":"Description 75","link":"Link 75"},{"title":"Title 76","description":"Description 76"},{"title":"Title 77","description":"Description 77"},{"title":"Title 78","description":"Description 78"},{"title":"Title 79","description":"Description 79","link":"Link 79"},{"title":"Title 80","description":"Description 80","link":"Link 80"},{"title":"Title 81","description":"Description 81","link":"Link 81"},{"title":"Title 82","description":"Description 82"},{"title":"Title 83","description":"Description 83"},{"title":"Title 84","description":"Description 84","link":"Link 84"},{"title":"Title 85","description":"Description 85","link":"Link 85"},{"title":"Title 86","description":"Description 86"},{"title":"Title 87","description":"Description 87","link":"Link 87"},{"title":"Title 88","description":"Description 88","link":"Link 88"},{"title":"Title 89","description":"Description 89"},{"title":"Title 90","description":"Description 90","link":"Link 90"},{"title":"Title 91","description":"Description 91","link":"Link 91"},{"title":"Title 92","description":"Description 92"},{"title":"Title 93","description":"Description 93"},{"title":"Title 94","description":"Description 94"},{"title":"Title 95","description":"Description 95"},{"title":"Title 96","description":"Description 96","link":"Link 96"},{"title":"Title 97","description":"Description 97","link":"Link 97"},{"title":"Title 98","description":"Description 98"},{"title":"Title 99","description":"Description 99"}]